{
    "timestamp": "2025-07-06 16:08:57",
    "market_sentiment": {
        "indicators": [
            {
                "name": "VIX (Fear Index)",
                "ticker": "^VIX",
                "price": "17.48",
                "direction": "UP"
            }
        ],
        "sentiment": "NEUTRAL / MIXED SIGNALS \ud83d\ude10"
    },
    "trade_ideas": [],
    "skipped_tickers": [],
    "vix_data": [
        {
            "date": "2025-06-06",
            "close": 16.77
        },
        {
            "date": "2025-06-09",
            "close": 17.16
        },
        {
            "date": "2025-06-10",
            "close": 16.95
        },
        {
            "date": "2025-06-11",
            "close": 17.26
        },
        {
            "date": "2025-06-12",
            "close": 18.02
        },
        {
            "date": "2025-06-13",
            "close": 20.82
        },
        {
            "date": "2025-06-16",
            "close": 19.11
        },
        {
            "date": "2025-06-17",
            "close": 21.6
        },
        {
            "date": "2025-06-18",
            "close": 20.14
        },
        {
            "date": "2025-06-20",
            "close": 20.62
        },
        {
            "date": "2025-06-23",
            "close": 19.83
        },
        {
            "date": "2025-06-24",
            "close": 17.48
        },
        {
            "date": "2025-06-25",
            "close": 16.76
        },
        {
            "date": "2025-06-26",
            "close": 16.59
        },
        {
            "date": "2025-06-27",
            "close": 16.32
        },
        {
            "date": "2025-06-30",
            "close": 16.73
        },
        {
            "date": "2025-07-01",
            "close": 16.83
        },
        {
            "date": "2025-07-02",
            "close": 16.64
        },
        {
            "date": "2025-07-03",
            "close": 16.38
        },
        {
            "date": "2025-07-04",
            "close": 17.48
        }
    ],
    "gamma_analysis": null,
    "top_strategies": [],
    "economic_calendar": [
        {
            "date": "2025-07-11 18:00:00",
            "country": "US",
            "event": "Monthly Budget Statement (Jun)",
            "currency": "USD",
            "previous": -316,
            "estimate": -350,
            "actual": null,
            "change": null,
            "impact": "Medium",
            "changePercentage": 0,
            "unit": "B"
        },
        {
            "date": "2025-07-11 18:00:00",
            "country": "US",
            "event": "Budget Balance (Jun)",
            "currency": "USD",
            "previous": -316,
            "estimate": null,
            "actual": null,
            "change": null,
            "impact": "Medium",
            "changePercentage": 0,
            "unit": "B"
        },
        {
            "date": "2025-07-10 18:30:00",
            "country": "US",
            "event": "Fed Daly Speech",
            "currency": "USD",
            "previous": null,
            "estimate": null,
            "actual": null,
            "change": null,
            "impact": "Medium",
            "changePercentage": 0,
            "unit": null
        },
        {
            "date": "2025-07-10 17:15:00",
            "country": "US",
            "event": "Fed Waller Speech",
            "currency": "USD",
            "previous": null,
            "estimate": null,
            "actual": null,
            "change": null,
            "impact": "Medium",
            "changePercentage": 0,
            "unit": null
        },
        {
            "date": "2025-07-10 14:00:00",
            "country": "US",
            "event": "Fed Musalem Speech",
            "currency": "USD",
            "previous": null,
            "estimate": null,
            "actual": null,
            "change": null,
            "impact": "Medium",
            "changePercentage": 0,
            "unit": null
        },
        {
            "date": "2025-07-10 12:30:00",
            "country": "US",
            "event": "Continuing Jobless Claims (Jun/28)",
            "currency": "USD",
            "previous": 1964,
            "estimate": 1967,
            "actual": null,
            "change": null,
            "impact": "High",
            "changePercentage": 0,
            "unit": "K"
        },
        {
            "date": "2025-07-10 12:30:00",
            "country": "US",
            "event": "Initial Jobless Claims (Jul/05)",
            "currency": "USD",
            "previous": 233,
            "estimate": 235,
            "actual": null,
            "change": null,
            "impact": "High",
            "changePercentage": 0,
            "unit": "K"
        },
        {
            "date": "2025-07-10 12:30:00",
            "country": "US",
            "event": "Jobless Claims 4-Week Average (Jul/05)",
            "currency": "USD",
            "previous": 241.5,
            "estimate": 243,
            "actual": null,
            "change": null,
            "impact": "High",
            "changePercentage": 0,
            "unit": "K"
        },
        {
            "date": "2025-07-09 18:00:00",
            "country": "US",
            "event": "FOMC Minutes",
            "currency": "USD",
            "previous": null,
            "estimate": null,
            "actual": null,
            "change": null,
            "impact": "High",
            "changePercentage": 0,
            "unit": null
        },
        {
            "date": "2025-07-09 17:00:00",
            "country": "US",
            "event": "Atlanta Fed GDPNow (Q2)",
            "currency": "USD",
            "previous": 2.6,
            "estimate": 2.6,
            "actual": null,
            "change": null,
            "impact": "Medium",
            "changePercentage": 0,
            "unit": "%"
        },
        {
            "date": "2025-07-09 14:30:00",
            "country": "US",
            "event": "EIA Gasoline Stocks Change (Jul/04)",
            "currency": "USD",
            "previous": 4.188,
            "estimate": null,
            "actual": null,
            "change": null,
            "impact": "Medium",
            "changePercentage": 0,
            "unit": "M"
        },
        {
            "date": "2025-07-09 14:30:00",
            "country": "US",
            "event": "EIA Crude Oil Stocks Change (Jul/04)",
            "currency": "USD",
            "previous": 3.845,
            "estimate": null,
            "actual": null,
            "change": null,
            "impact": "Medium",
            "changePercentage": 0,
            "unit": "M"
        },
        {
            "date": "2025-07-09 11:00:00",
            "country": "US",
            "event": "MBA 30-Year Mortgage Rate (Jul/04)",
            "currency": "USD",
            "previous": 6.79,
            "estimate": null,
            "actual": null,
            "change": null,
            "impact": "Medium",
            "changePercentage": 0,
            "unit": "%"
        },
        {
            "date": "2025-07-08 20:30:00",
            "country": "US",
            "event": "API Crude Oil Stock Change (Jul/04)",
            "currency": "USD",
            "previous": 0.68,
            "estimate": null,
            "actual": null,
            "change": null,
            "impact": "Medium",
            "changePercentage": 0,
            "unit": null
        },
        {
            "date": "2025-07-08 19:00:00",
            "country": "US",
            "event": "BoE Consumer Credit",
            "currency": "USD",
            "previous": 17.87,
            "estimate": 10.6,
            "actual": null,
            "change": null,
            "impact": "Medium",
            "changePercentage": 0,
            "unit": "B"
        },
        {
            "date": "2025-07-07 19:30:00",
            "country": "US",
            "event": "CFTC Nasdaq 100 speculative net positions",
            "currency": "USD",
            "previous": 16.5,
            "estimate": null,
            "actual": null,
            "change": null,
            "impact": "Medium",
            "changePercentage": 0,
            "unit": "K"
        },
        {
            "date": "2025-07-07 19:30:00",
            "country": "US",
            "event": "CFTC S&P 500 speculative net positions",
            "currency": "USD",
            "previous": -144.8,
            "estimate": null,
            "actual": null,
            "change": null,
            "impact": "Medium",
            "changePercentage": 0,
            "unit": "K"
        },
        {
            "date": "2025-07-07 19:30:00",
            "country": "US",
            "event": "CFTC Gold Speculative net positions",
            "currency": "USD",
            "previous": 195,
            "estimate": null,
            "actual": null,
            "change": null,
            "impact": "Medium",
            "changePercentage": 0,
            "unit": "K"
        },
        {
            "date": "2025-07-07 19:30:00",
            "country": "US",
            "event": "CFTC Crude Oil speculative net positions",
            "currency": "USD",
            "previous": 233,
            "estimate": null,
            "actual": null,
            "change": null,
            "impact": "Medium",
            "changePercentage": 0,
            "unit": "K"
        }
    ],
    "earnings_calendar": [],
    "top_gainers": [],
    "top_losers": [],
    "indices": [
        {
            "symbol": "^VIX",
            "name": "CBOE Volatility Index",
            "price": 17.48,
            "changesPercentage": 5.04808,
            "change": 0.84,
            "dayLow": 16.92,
            "dayHigh": 17.67,
            "yearHigh": 35.05,
            "yearLow": 15.53,
            "marketCap": 0,
            "priceAvg50": 18.5274,
            "priceAvg200": 22.3272,
            "exchange": "INDEX",
            "volume": 0,
            "avgVolume": 0,
            "open": 16.93,
            "previousClose": 16.64,
            "eps": null,
            "pe": null,
            "earningsAnnouncement": null,
            "sharesOutstanding": null,
            "timestamp": 1751643001
        },
        {
            "symbol": "^GSPC",
            "name": "S&P 500",
            "price": 6279.35,
            "changesPercentage": 0.83389,
            "change": 51.93,
            "dayLow": 6246.46,
            "dayHigh": 6284.65,
            "yearHigh": 6284.65,
            "yearLow": 4835.04,
            "marketCap": 0,
            "priceAvg50": 5887.552,
            "priceAvg200": 5842.7715,
            "exchange": "INDEX",
            "volume": 1822312000,
            "avgVolume": 5267143770,
            "open": 6246.46,
            "previousClose": 6227.42,
            "eps": null,
            "pe": null,
            "earningsAnnouncement": null,
            "sharesOutstanding": null,
            "timestamp": 1751564591
        },
        {
            "symbol": "^DJI",
            "name": "Dow Jones Industrial Average",
            "price": 44828.53,
            "changesPercentage": 0.77355,
            "change": 344.11,
            "dayLow": 44550.42,
            "dayHigh": 44885.83,
            "yearHigh": 45073.63,
            "yearLow": 36611.78,
            "marketCap": 0,
            "priceAvg50": 42185.08,
            "priceAvg200": 42650.875,
            "exchange": "INDEX",
            "volume": 346629174,
            "avgVolume": 598043114,
            "open": 44565.75,
            "previousClose": 44484.42,
            "eps": null,
            "pe": null,
            "earningsAnnouncement": null,
            "sharesOutstanding": null,
            "timestamp": 1751564591
        },
        {
            "symbol": "^IXIC",
            "name": "NASDAQ Composite",
            "price": 20601.102,
            "changesPercentage": 1.01996,
            "change": 208.002,
            "dayLow": 20480.223,
            "dayHigh": 20624.51,
            "yearHigh": 20624.51,
            "yearLow": 14784.03,
            "marketCap": 0,
            "priceAvg50": 18993.674,
            "priceAvg200": 18729.018,
            "exchange": "INDEX",
            "volume": 5716052000,
            "avgVolume": 10627483770,
            "open": 20497.664,
            "previousClose": 20393.1,
            "eps": null,
            "pe": null,
            "earningsAnnouncement": null,
            "sharesOutstanding": null,
            "timestamp": 1751566561
        }
    ]
}